plucky/__init__.py
plucky/compat.py
plucky/structural.py
plucky-0.4.3.dist-info/DESCRIPTION.rst
plucky-0.4.3.dist-info/METADATA
plucky-0.4.3.dist-info/RECORD
plucky-0.4.3.dist-info/WHEEL
plucky-0.4.3.dist-info/metadata.json
plucky-0.4.3.dist-info/top_level.txt
