Metadata-Version: 1.1
Name: plucky
Version: 0.4.3
Summary: Plucking (deep) keys/paths safely from python collections has never been easier.
Home-page: https://github.com/randomir/plucky
Author: Radomir Stevanovic
Author-email: radomir.stevanovic@gmail.com
License: MIT
Keywords: pluck itemgetter safe nested get
Platform: UNKNOWN
Classifier: Development Status :: 4 - Beta
Classifier: Intended Audience :: Developers
Classifier: Programming Language :: Python
Classifier: Programming Language :: Python :: 2
Classifier: Programming Language :: Python :: 2.6
Classifier: Programming Language :: Python :: 2.7
Classifier: Programming Language :: Python :: 3
Classifier: Programming Language :: Python :: 3.3
Classifier: Programming Language :: Python :: 3.4
Classifier: Programming Language :: Python :: 3.5
Classifier: Programming Language :: Python :: 3.6
Classifier: License :: OSI Approved :: MIT License
Classifier: Operating System :: OS Independent
Classifier: Topic :: Software Development :: Libraries :: Python Modules
